Owls/FoamFrame.py
Owls/MultiFrame.py
Owls/__init__.py
Owls/foam.py
Owls/io.py
Owls/mesh.py
Owls/plot.py
Owls/version.py
Owls-0.9.1.data/data/scripts/snap.py
Owls-0.9.1.dist-info/METADATA
Owls-0.9.1.dist-info/RECORD
Owls-0.9.1.dist-info/WHEEL
Owls-0.9.1.dist-info/top_level.txt
